pyban/__init__.py
pyban/country.py
pyban/iban.py
pyban_swift-0.1.dist-info/LICENSE
pyban_swift-0.1.dist-info/METADATA
pyban_swift-0.1.dist-info/WHEEL
pyban_swift-0.1.dist-info/top_level.txt
pyban_swift-0.1.dist-info/RECORD
